Metadata-Version: 2.1
Name: nr.cliparser
Version: 0.1.1
Summary: Extensible CLI parser.
Home-page: https://gitlab.niklasrosenstein.com/NiklasRosenstein/python/nr.cliparser
Author: Niklas Rosenstein
Author-email: rosensteinniklas@gmail.com
License: MIT
Platform: UNKNOWN
